lwrad/__init__.py
lwrad/__main__.py
lwrad/cpu.py
lwrad/cuda.py
lwrad/main.py
lwrad/utils.py
lwrad-0.5.4.dist-info/LICENSE
lwrad-0.5.4.dist-info/METADATA
lwrad-0.5.4.dist-info/WHEEL
lwrad-0.5.4.dist-info/top_level.txt
lwrad-0.5.4.dist-info/RECORD
