Metadata-Version: 2.1
Name: lwrad
Version: 0.5.4
Summary: Calculating the radiation spectrum of relativistic particles using the Lienard-Wiechert potential.
Author-email: xsgeng <xsgeng@siom.ac.cn>
License:                     GNU GENERAL PUBLIC LICENSE
Project-URL: Repository, https://github.com/xsgeng/lwrad.git
Keywords: Radiation Spectrum,Plasma Physics
Classifier: Development Status :: 3 - Alpha
Classifier: Intended Audience :: Science/Research
Classifier: Programming Language :: Python :: 3.9
Requires-Python: >=3.9
License-File: LICENSE
Requires-Dist: typer
Requires-Dist: tqdm
Requires-Dist: h5py
Requires-Dist: numpy
Requires-Dist: numba
Requires-Dist: scipy
